[
  {
    "created_time": "2019-01-08T09:05:04+0000",
    "id": "1481985248595237_1862606550533103",
    "message": "Hi Everyone. Our first Tuesday Code Club session will be the 15th Jan @ 5pm\n\nWe will be looking at the new Scratch 3 editor"
  },
  {
    "created_time": "2019-01-01T17:57:53+0000",
    "id": "1481985248595237_1853574981436260",
    "message": "Happy New Year Everyone. I will let you all know when the Code Club sessions can resume at St Marys. In the meantime, take a look at Scratch 3. It should be replacing Scratch 2 shortly \ud83d\ude0a\ud83d\ude0a\ud83d\ude0a"
  },
  {
    "attachments": {
      "data": [
        {
          "description": "Our largest turnout to date. Thank you so much for attending and showing such enthusiasm. A massive thanks to parents and Library staff for their support this past year. Looking forward to seeing you all at St Marys in the new year. Look out for our starting date. A very Merry Christmas to you all - Stewart, Yvonne, John & Brian. :-)",
          "media": {
            "image": {
              "height": 720,
              "src": "https://scontent.fbhx6-1.fna.fbcdn.net/v/t1.6435-9/46511345_1798372253623200_6543922428291055616_n.jpg?stp=dst-jpg_p720x720&_nc_cat=102&ccb=1-7&_nc_sid=730e14&_nc_ohc=8qFEC_TSYb8AX-0jKFC&_nc_ht=scontent.fbhx6-1.fna&edm=AKK4YLsEAAAA&oh=00_AfDLBvK0uHaylCXL8ZUasjfDycBMOj5rpi0O3audTmTIeg&oe=654E194A",
              "width": 1250
            }
          },
          "target": {
            "id": "1798372246956534",
            "url": "https://www.facebook.com/LichfieldCoders/photos/a.1482002635260165/1798372246956534/?type=3"
          },
          "type": "photo",
          "url": "https://www.facebook.com/LichfieldCoders/photos/a.1482002635260165/1798372246956534/?type=3"
        }
      ]
    },
    "created_time": "2018-11-21T15:03:14+0000",
    "id": "1481985248595237_1798375423622883",
    "message": "Our largest turnout to date. Thank you so much for attending and showing such enthusiasm. A massive thanks to parents and Library staff for their support this past year. Looking forward to seeing you all at St Marys in the new year. Look out for our starting date. A very Merry Christmas to you all - Stewart, Yvonne, John & Brian. :-)"
  },
  {
    "attachments": {
      "data": [
        {
          "description": "Tuesday evening we all had a go at BBC Micro Bit programming. Everybody got the hang of it real quick and we had some brilliant creations.\nWe will be using the BBC Micro Bit more next year, so get your thinking caps on.",
          "media": {
            "image": {
              "height": 720,
              "src": "https://scontent.fbhx6-1.fna.fbcdn.net/v/t1.6435-9/46496295_1798365530290539_903528022336864256_n.jpg?stp=dst-jpg_p720x720&_nc_cat=106&ccb=1-7&_nc_sid=cdbe9c&_nc_ohc=24CiJSdTjQQAX-xaFN3&_nc_ht=scontent.fbhx6-1.fna&edm=AKK4YLsEAAAA&oh=00_AfCI5hmHHS4mOv9AYu_skGldFFJmSe5Zqdn0PWtDoGiy5A&oe=654E2F69",
              "width": 887
            }
          },
          "subattachments": {
            "data": [
              {
                "description": "Adding numbers on the Micro Bit and then shaking it to display the answer!",
                "media": {
                  "image": {
                    "height": 720,
                    "src": "https://scontent.fbhx6-1.fna.fbcdn.net/v/t1.6435-9/46496295_1798365530290539_903528022336864256_n.jpg?stp=dst-jpg_p720x720&_nc_cat=106&ccb=1-7&_nc_sid=cdbe9c&_nc_ohc=24CiJSdTjQQAX-xaFN3&_nc_ht=scontent.fbhx6-1.fna&edm=AKK4YLsEAAAA&oh=00_AfCI5hmHHS4mOv9AYu_skGldFFJmSe5Zqdn0PWtDoGiy5A&oe=654E2F69",
                    "width": 887
                  }
                },
                "target": {
                  "id": "1798365523623873",
                  "url": "https://www.facebook.com/LichfieldCoders/photos/a.1798365466957212/1798365523623873/?type=3"
                },
                "title": "Tuesday Codeclub",
                "type": "photo",
                "url": "https://www.facebook.com/LichfieldCoders/photos/a.1798365466957212/1798365523623873/?type=3"
              },
              {
                "media": {
                  "image": {
                    "height": 720,
                    "src": "https://scontent.fbhx6-1.fna.fbcdn.net/v/t1.6435-9/46499350_1798365543623871_9002522713960480768_n.jpg?stp=dst-jpg_p720x720&_nc_cat=110&ccb=1-7&_nc_sid=cdbe9c&_nc_ohc=nsq14JRw7qwAX_4Nmpn&_nc_ht=scontent.fbhx6-1.fna&edm=AKK4YLsEAAAA&oh=00_AfAaWbXvGeSD9s4Tjo_gjRNXFvj2eghxGkXZbjqTXR9Lbw&oe=654E2BA1",
                    "width": 815
                  }
                },
                "target": {
                  "id": "1798365536957205",
                  "url": "https://www.facebook.com/LichfieldCoders/photos/a.1798365466957212/1798365536957205/?type=3"
                },
                "title": "Tuesday Codeclub",
                "type": "photo",
                "url": "https://www.facebook.com/LichfieldCoders/photos/a.1798365466957212/1798365536957205/?type=3"
              },
              {
                "media": {
                  "image": {
                    "height": 720,
                    "src": "https://scontent.fbhx6-1.fna.fbcdn.net/v/t1.6435-9/46513479_1798365520290540_8041123615082545152_n.jpg?stp=dst-jpg_p720x720&_nc_cat=108&ccb=1-7&_nc_sid=cdbe9c&_nc_ohc=jWbONhAdwFUAX8x_H4i&_nc_ht=scontent.fbhx6-1.fna&edm=AKK4YLsEAAAA&oh=00_AfClxFVaWUuc7ydowEMmiw_QR_h2Z_0jMU4Jak_t1vAHeA&oe=654E24AE",
                    "width": 1438
                  }
                },
                "target": {
                  "id": "1798365513623874",
                  "url": "https://www.facebook.com/LichfieldCoders/photos/a.1798365466957212/1798365513623874/?type=3"
                },
                "title": "Tuesday Codeclub",
                "type": "photo",
                "url": "https://www.facebook.com/LichfieldCoders/photos/a.1798365466957212/1798365513623874/?type=3"
              },
              {
                "media": {
                  "image": {
                    "height": 720,
                    "src": "https://scontent.fbhx6-1.fna.fbcdn.net/v/t1.6435-9/46492144_1798365506957208_7240700023602675712_n.jpg?stp=dst-jpg_p720x720&_nc_cat=100&ccb=1-7&_nc_sid=cdbe9c&_nc_ohc=XAuk4cyOLGUAX9dKz0s&_nc_ht=scontent.fbhx6-1.fna&edm=AKK4YLsEAAAA&oh=00_AfB-w0D0UjbfOgClelYIbLUPmpOsN7DzhrtGVguRYtWmJg&oe=654E1484",
                    "width": 1453
                  }
                },
                "target": {
                  "id": "1798365503623875",
                  "url": "https://www.facebook.com/LichfieldCoders/photos/a.1798365466957212/1798365503623875/?type=3"
                },
                "title": "Tuesday Codeclub",
                "type": "photo",
                "url": "https://www.facebook.com/LichfieldCoders/photos/a.1798365466957212/1798365503623875/?type=3"
              },
              {
                "description": "Making the Micro Bit smile and Frown at the press of a button.",
                "media": {
                  "image": {
                    "height": 720,
                    "src": "https://scontent.fbhx6-1.fna.fbcdn.net/v/t1.6435-9/46508094_1798365580290534_3932103144296677376_n.jpg?stp=dst-jpg_p720x720&_nc_cat=109&ccb=1-7&_nc_sid=cdbe9c&_nc_ohc=2E6WLUfXBzIAX_SeCdP&_nc_ht=scontent.fbhx6-1.fna&edm=AKK4YLsEAAAA&oh=00_AfApyMojVs_JQO6rALJNmY1oFXln7PraOxoFAUNmjqClDQ&oe=654E0738",
                    "width": 824
                  }
                },
                "target": {
                  "id": "1798365566957202",
                  "url": "https://www.facebook.com/LichfieldCoders/photos/a.1798365466957212/1798365566957202/?type=3"
                },
                "title": "Tuesday Codeclub",
                "type": "photo",
                "url": "https://www.facebook.com/LichfieldCoders/photos/a.1798365466957212/1798365566957202/?type=3"
              }
            ]
          },
          "title": "Tuesday Codeclub",
          "type": "new_album",
          "url": "https://www.facebook.com/media/set/?set=ms.c.eJxFy8kNACAMA8GOUGLjHP03xiMIvqNdzy6GBAZYyeUXGK2E6YFPsR%7E%3BYwC9iFhzenxFF.bps.a.1798365466957212&type=1"
        }
      ]
    },
    "created_time": "2018-11-21T14:58:29+0000",
    "id": "1481985248595237_1798365503623875",
    "message": "Tuesday evening we all had a go at BBC Micro Bit programming. Everybody got the hang of it real quick and we had some brilliant creations.\nWe will be using the BBC Micro Bit more next year, so get your thinking caps on."
  },
  {
    "attachments": {
      "data": [
        {
          "media": {
            "image": {
              "height": 405,
              "src": "https://scontent.fbhx6-1.fna.fbcdn.net/v/t15.13418-10/44369292_255837195290963_4481605314596044800_n.jpg?stp=dst-jpg_s720x720&_nc_cat=106&ccb=1-7&_nc_sid=ad6a45&_nc_ohc=MZefWCMVrnQAX-Q7tU-&_nc_ht=scontent.fbhx6-1.fna&edm=AKK4YLsEAAAA&oh=00_AfAZzuu9jD7feO3CtW4uFzK8YHQ7SXE9offpcWbxEOPqBA&oe=652ADE6F",
              "width": 720
            }
          },
          "target": {
            "id": "2173213839598873",
            "url": "https://www.facebook.com/720665616418529/videos/2173213839598873"
          },
          "title": "VEX IQ Robot Programming",
          "type": "video_inline",
          "url": "https://www.facebook.com/720665616418529/videos/2173213839598873"
        }
      ]
    },
    "created_time": "2018-11-11T12:25:28+0000",
    "id": "1481985248595237_1785855398208219",
    "message": "We modified our VEX Robot to have flashing lights and a siren. Well done guys. Next time we are going to investigate the colour sensor and precise turning using the Gyro."
  },
  {
    "attachments": {
      "data": [
        {
          "description": "Yesterday we were coding with the VEX IQ Robot, the BBC Micro Bit, Raspberry PI and Scratch. Thank you to all who dropped in, including some new volunteers to help with our sessions.",
          "media": {
            "image": {
              "height": 791,
              "src": "https://scontent.fbhx6-1.fna.fbcdn.net/v/t1.6435-9/46076612_1785835564876869_843163798884843520_n.jpg?stp=dst-jpg_p720x720&_nc_cat=111&ccb=1-7&_nc_sid=cdbe9c&_nc_ohc=x2HYzJP3QX8AX-81Hqq&_nc_ht=scontent.fbhx6-1.fna&edm=AKK4YLsEAAAA&oh=00_AfB7LB_lJwN2k4Dd7y1LQDNdKl75ixFvOdMGESKIHvnkvg&oe=654E2A56",
              "width": 720
            }
          },
          "subattachments": {
            "data": [
              {
                "description": "Using MODKit to program the VEX IQ Robot.",
                "media": {
                  "image": {
                    "height": 791,
                    "src": "https://scontent.fbhx6-1.fna.fbcdn.net/v/t1.6435-9/46076612_1785835564876869_843163798884843520_n.jpg?stp=dst-jpg_p720x720&_nc_cat=111&ccb=1-7&_nc_sid=cdbe9c&_nc_ohc=x2HYzJP3QX8AX-81Hqq&_nc_ht=scontent.fbhx6-1.fna&edm=AKK4YLsEAAAA&oh=00_AfB7LB_lJwN2k4Dd7y1LQDNdKl75ixFvOdMGESKIHvnkvg&oe=654E2A56",
                    "width": 720
                  }
                },
                "target": {
                  "id": "1785835558210203",
                  "url": "https://www.facebook.com/LichfieldCoders/photos/a.1785835458210213/1785835558210203/?type=3"
                },
                "title": "Saturday Code Club",
                "type": "photo",
                "url": "https://www.facebook.com/LichfieldCoders/photos/a.1785835458210213/1785835558210203/?type=3"
              },
              {
                "description": "Games programming in Scratch and BBC Micro BIT.",
                "media": {
                  "image": {
                    "height": 720,
                    "src": "https://scontent.fbhx6-1.fna.fbcdn.net/v/t1.6435-9/45825711_1785835538210205_8532658321184784384_n.jpg?stp=dst-jpg_p720x720&_nc_cat=103&ccb=1-7&_nc_sid=cdbe9c&_nc_ohc=GvrUUVaGzFgAX9jedUQ&_nc_ht=scontent.fbhx6-1.fna&edm=AKK4YLsEAAAA&oh=00_AfAhtdoLlvY8n-MMH78cHFsTqct64QzYNhQet_53xIeSVw&oe=654E2299",
                    "width": 1094
                  }
                },
                "target": {
                  "id": "1785835524876873",
                  "url": "https://www.facebook.com/LichfieldCoders/photos/a.1785835458210213/1785835524876873/?type=3"
                },
                "title": "Saturday Code Club",
                "type": "photo",
                "url": "https://www.facebook.com/LichfieldCoders/photos/a.1785835458210213/1785835524876873/?type=3"
              },
              {
                "description": "In the foreground, a Python game using an accelerometer for input. In the background, programming the VEX IQ Robot.",
                "media": {
                  "image": {
                    "height": 1115,
                    "src": "https://scontent.fbhx6-1.fna.fbcdn.net/v/t1.6435-9/46093510_1785835528210206_7555672137449603072_n.jpg?stp=dst-jpg_p720x720&_nc_cat=101&ccb=1-7&_nc_sid=cdbe9c&_nc_ohc=97sMEWirMzAAX_Z7SD7&_nc_ht=scontent.fbhx6-1.fna&edm=AKK4YLsEAAAA&oh=00_AfBxI8liv9fd-PdwIjl4oYuNvUVOr7hBmTAnPrU_GqnyLw&oe=654E1E5F",
                    "width": 720
                  }
                },
                "target": {
                  "id": "1785835521543540",
                  "url": "https://www.facebook.com/LichfieldCoders/photos/a.1785835458210213/1785835521543540/?type=3"
                },
                "title": "Saturday Code Club",
                "type": "photo",
                "url": "https://www.facebook.com/LichfieldCoders/photos/a.1785835458210213/1785835521543540/?type=3"
              }
            ]
          },
          "title": "Saturday Code Club",
          "type": "new_album",
          "url": "https://www.facebook.com/media/set/?set=ms.c.eJxNyLERADAIAsCNcoIi7D9ZmhT58uEoLSlEsfrgBSfe%7E_AtoWlMXBNQKNQ%7E-%7E-.bps.a.1785835458210213&type=1"
        }
      ]
    },
    "created_time": "2018-11-11T12:06:48+0000",
    "id": "1481985248595237_5195406647253060",
    "message": "Yesterday we were coding with the VEX IQ Robot, the BBC Micro Bit, Raspberry PI and Scratch. Thank you to all who dropped in, including some new volunteers to help with our sessions."
  },
  {
    "attachments": {
      "data": [
        {
          "description": "0 went \u00b7 0 interested",
          "media": {
            "image": {
              "height": 720,
              "src": "https://scontent.fbhx6-1.fna.fbcdn.net/v/t1.6435-9/45742673_1784466285013797_2586512490577788928_n.jpg?stp=c120.0.720.720a_dst-jpg&_nc_cat=106&ccb=1-7&_nc_sid=b386c4&_nc_ohc=Dqlf5i7MXJQAX9AFa2v&_nc_ht=scontent.fbhx6-1.fna&edm=AKK4YLsEAAAA&oh=00_AfCON1hCzCAz73u09zSOfEfcA4lOc3zSTJKivm0NrwM9Xg&oe=654E1647",
              "width": 720
            }
          },
          "target": {
            "id": "601731180260570",
            "url": "https://www.facebook.com/events/601731180260570/"
          },
          "title": "Lichfield Library Code Club",
          "type": "event",
          "url": "https://www.facebook.com/events/601731180260570/"
        }
      ]
    },
    "created_time": "2018-11-10T10:09:14+0000",
    "id": "1481985248595237_1784465568347202",
    "message": "Saturday Code Club on Today.\nAll Welcome. As always sessions are free. \ud83d\ude0a"
  },
  {
    "created_time": "2018-11-06T20:02:49+0000",
    "id": "1481985248595237_1779916718802087",
    "message": "Saturday Code Club 10th November. 1pm - 3pm\nScratch, Raspberry Pi, Micro Bit.\nLichfield Library \nEverybody Welcome. \ud83d\ude0a"
  },
  {
    "created_time": "2018-11-01T20:32:05+0000",
    "id": "1481985248595237_1773507892776303",
    "message": "Next Saturday CodeClub session planned for  10th November. Will confirm by Wednesday 7th November."
  },
  {
    "attachments": {
      "data": [
        {
          "description": "Thank you to all that attended todays Code Club. \ud83d\ude0a \n\nWe will be back in November and then will take a break while the Library moves to it\u2019s new home in January. \n\nA big thank you to Yvonne Smith and staff for hosting us.",
          "media": {
            "image": {
              "height": 596,
              "src": "https://scontent.fbhx6-1.fna.fbcdn.net/v/t1.6435-9/43250736_1736718303121929_2832348082069307392_n.jpg?_nc_cat=100&ccb=1-7&_nc_sid=dd63ad&_nc_ohc=ubHpyGqbuFAAX_iX96a&_nc_ht=scontent.fbhx6-1.fna&edm=AKK4YLsEAAAA&oh=00_AfAvZfFGz-1rxuQz_G0CtLqsrnNWEm1GcqTwkw9VFKy86Q&oe=654E0765",
              "width": 960
            }
          },
          "target": {
            "id": "1736718296455263",
            "url": "https://www.facebook.com/LichfieldCoders/photos/a.1494843043976124/1736718296455263/?type=3"
          },
          "type": "photo",
          "url": "https://www.facebook.com/LichfieldCoders/photos/a.1494843043976124/1736718296455263/?type=3"
        }
      ]
    },
    "created_time": "2018-10-06T22:06:26+0000",
    "id": "1481985248595237_1736718333121926",
    "message": "Thank you to all that attended todays Code Club. \ud83d\ude0a \n\nWe will be back in November and then will take a break while the Library moves to it\u2019s new home in January. \n\nA big thank you to Yvonne Smith and staff for hosting us."
  },
  {
    "created_time": "2018-10-05T18:16:25+0000",
    "id": "1481985248595237_1735232553270504",
    "message": "Saturday Code Club is on tomorrow 1pm - 3pm\nin Lichfield Library.\n\nLooking forward to seeing you if you have an interest in computer programming.\n\nWe will be showing Raspberry Pi, Micro Bit, Scratch and the VEX IQ Robot."
  },
  {
    "created_time": "2018-09-11T11:22:16+0000",
    "id": "1481985248595237_1706891252771301",
    "message": "Tuesday night Code Club sessions resume tonight."
  },
  {
    "attachments": {
      "data": [
        {
          "description": "Thank you to Tim Wilson, Midlands Code Club Co-ordinator for visiting our club last Tuesday evening. \ud83d\ude0a",
          "media": {
            "image": {
              "height": 720,
              "src": "https://scontent.fbhx6-1.fna.fbcdn.net/v/t1.6435-9/36852933_1613020978824996_2111008432080289792_n.jpg?_nc_cat=104&ccb=1-7&_nc_sid=dd63ad&_nc_ohc=bKldsqQGzPQAX8DPq90&_nc_ht=scontent.fbhx6-1.fna&edm=AKK4YLsEAAAA&oh=00_AfDS2mtsrwyW2vzg9eQhoA9ivqBGFmNQIOHaqly-kSoxsQ&oe=654E2965",
              "width": 960
            }
          },
          "target": {
            "id": "1613020975491663",
            "url": "https://www.facebook.com/LichfieldCoders/photos/a.1494843043976124/1613020975491663/?type=3"
          },
          "type": "photo",
          "url": "https://www.facebook.com/LichfieldCoders/photos/a.1494843043976124/1613020975491663/?type=3"
        }
      ]
    },
    "created_time": "2018-07-10T06:36:37+0000",
    "id": "1481985248595237_1613020995491661",
    "message": "Thank you to Tim Wilson, Midlands Code Club Co-ordinator for visiting our club last Tuesday evening. \ud83d\ude0a"
  },
  {
    "attachments": {
      "data": [
        {
          "description": "On Sunday Jonathon and I took Code Club to the Cosford Air Show. A great day was had by all.",
          "media": {
            "image": {
              "height": 720,
              "src": "https://scontent.fbhx6-1.fna.fbcdn.net/v/t1.6435-9/35126877_1570694613057633_5479583172465262592_n.jpg?stp=dst-jpg_p720x720&_nc_cat=102&ccb=1-7&_nc_sid=cdbe9c&_nc_ohc=Lk0z40PJKBYAX-7HBsy&_nc_ht=scontent.fbhx6-1.fna&edm=AKK4YLsEAAAA&oh=00_AfBtwtlShrjO3NbYwwhkQNh2xX5iwS001G_Hjrw22-8UJg&oe=654E35D7",
              "width": 960
            }
          },
          "subattachments": {
            "data": [
              {
                "media": {
                  "image": {
                    "height": 720,
                    "src": "https://scontent.fbhx6-1.fna.fbcdn.net/v/t1.6435-9/35126877_1570694613057633_5479583172465262592_n.jpg?stp=dst-jpg_p720x720&_nc_cat=102&ccb=1-7&_nc_sid=cdbe9c&_nc_ohc=Lk0z40PJKBYAX-7HBsy&_nc_ht=scontent.fbhx6-1.fna&edm=AKK4YLsEAAAA&oh=00_AfBtwtlShrjO3NbYwwhkQNh2xX5iwS001G_Hjrw22-8UJg&oe=654E35D7",
                    "width": 960
                  }
                },
                "target": {
                  "id": "1570694603057634",
                  "url": "https://www.facebook.com/LichfieldCoders/photos/a.1570694216391006/1570694603057634/?type=3"
                },
                "title": "Code Club at RAF Cosford",
                "type": "photo",
                "url": "https://www.facebook.com/LichfieldCoders/photos/a.1570694216391006/1570694603057634/?type=3"
              },
              {
                "media": {
                  "image": {
                    "height": 720,
                    "src": "https://scontent.fbhx6-1.fna.fbcdn.net/v/t1.6435-9/35077462_1570694423057652_6962118270006591488_n.jpg?stp=dst-jpg_p720x720&_nc_cat=101&ccb=1-7&_nc_sid=cdbe9c&_nc_ohc=gH1mfW3jzCwAX-jvoAW&_nc_ht=scontent.fbhx6-1.fna&edm=AKK4YLsEAAAA&oh=00_AfCZST8mA5ySemLrqx5sD1ZCpitEAyJ80wTqYFBPpBajOQ&oe=654E07D9",
                    "width": 960
                  }
                },
                "target": {
                  "id": "1570694416390986",
                  "url": "https://www.facebook.com/LichfieldCoders/photos/a.1570694216391006/1570694416390986/?type=3"
                },
                "title": "Code Club at RAF Cosford",
                "type": "photo",
                "url": "https://www.facebook.com/LichfieldCoders/photos/a.1570694216391006/1570694416390986/?type=3"
              },
              {
                "media": {
                  "image": {
                    "height": 720,
                    "src": "https://scontent.fbhx6-1.fna.fbcdn.net/v/t1.6435-9/35296495_1570694443057650_1849724899787014144_n.jpg?stp=dst-jpg_p720x720&_nc_cat=108&ccb=1-7&_nc_sid=cdbe9c&_nc_ohc=5smNyiojmqgAX-WpCUV&_nc_ht=scontent.fbhx6-1.fna&edm=AKK4YLsEAAAA&oh=00_AfB-R77H-SyTy24NsyKFceZM0W3HGBuPXXADMC8NWZh0PA&oe=654E0E6D",
                    "width": 960
                  }
                },
                "target": {
                  "id": "1570694439724317",
                  "url": "https://www.facebook.com/LichfieldCoders/photos/a.1570694216391006/1570694439724317/?type=3"
                },
                "title": "Code Club at RAF Cosford",
                "type": "photo",
                "url": "https://www.facebook.com/LichfieldCoders/photos/a.1570694216391006/1570694439724317/?type=3"
              },
              {
                "media": {
                  "image": {
                    "height": 720,
                    "src": "https://scontent.fbhx6-1.fna.fbcdn.net/v/t1.6435-9/35151700_1570694259724335_7130027667096600576_n.jpg?stp=dst-jpg_p720x720&_nc_cat=104&ccb=1-7&_nc_sid=cdbe9c&_nc_ohc=Dxp6Mr9Q2nAAX9iv9Vg&_nc_ht=scontent.fbhx6-1.fna&edm=AKK4YLsEAAAA&oh=00_AfB2NRFjGgGX7uM1aGas1XrRNwfpCXA-mk1zIR0yEb-9ww&oe=654E235B",
                    "width": 960
                  }
                },
                "target": {
                  "id": "1570694256391002",
                  "url": "https://www.facebook.com/LichfieldCoders/photos/a.1570694216391006/1570694256391002/?type=3"
                },
                "title": "Code Club at RAF Cosford",
                "type": "photo",
                "url": "https://www.facebook.com/LichfieldCoders/photos/a.1570694216391006/1570694256391002/?type=3"
              },
              {
                "media": {
                  "image": {
                    "height": 720,
                    "src": "https://scontent.fbhx6-1.fna.fbcdn.net/v/t1.6435-9/35062521_1570694326390995_513343265836105728_n.jpg?stp=dst-jpg_p720x720&_nc_cat=100&ccb=1-7&_nc_sid=cdbe9c&_nc_ohc=U8AAkbveXLoAX8k_t3l&_nc_ht=scontent.fbhx6-1.fna&edm=AKK4YLsEAAAA&oh=00_AfCdz0f-IGN94l8xfhGenKsto10jl4Mz76Men9GfstOl8Q&oe=654E0D68",
                    "width": 960
                  }
                },
                "target": {
                  "id": "1570694316390996",
                  "url": "https://www.facebook.com/LichfieldCoders/photos/a.1570694216391006/1570694316390996/?type=3"
                },
                "title": "Code Club at RAF Cosford",
                "type": "photo",
                "url": "https://www.facebook.com/LichfieldCoders/photos/a.1570694216391006/1570694316390996/?type=3"
              },
              {
                "media": {
                  "image": {
                    "height": 720,
                    "src": "https://scontent.fbhx6-1.fna.fbcdn.net/v/t1.6435-9/35244540_1570694483057646_9122481915041939456_n.jpg?stp=dst-jpg_p720x720&_nc_cat=104&ccb=1-7&_nc_sid=cdbe9c&_nc_ohc=7LbsBuWaZM8AX9ImWcO&_nc_ht=scontent.fbhx6-1.fna&edm=AKK4YLsEAAAA&oh=00_AfBjkvltENSCCSGTQdI0ihz_vfB6mZ9e2OrmX5lxZIWq3Q&oe=654E3290",
                    "width": 960
                  }
                },
                "target": {
                  "id": "1570694479724313",
                  "url": "https://www.facebook.com/LichfieldCoders/photos/a.1570694216391006/1570694479724313/?type=3"
                },
                "title": "Code Club at RAF Cosford",
                "type": "photo",
                "url": "https://www.facebook.com/LichfieldCoders/photos/a.1570694216391006/1570694479724313/?type=3"
              },
              {
                "media": {
                  "image": {
                    "height": 720,
                    "src": "https://scontent.fbhx6-1.fna.fbcdn.net/v/t1.6435-9/35062865_1570694553057639_1991002321366024192_n.jpg?stp=dst-jpg_p720x720&_nc_cat=103&ccb=1-7&_nc_sid=cdbe9c&_nc_ohc=VAeKFbWn1tsAX8Dqw8S&_nc_ht=scontent.fbhx6-1.fna&edm=AKK4YLsEAAAA&oh=00_AfB2O3NK2cyl04NrakDQ4pDJCYxG0oviE32lx__6cd-jxQ&oe=654E32F1",
                    "width": 960
                  }
                },
                "target": {
                  "id": "1570694543057640",
                  "url": "https://www.facebook.com/LichfieldCoders/photos/a.1570694216391006/1570694543057640/?type=3"
                },
                "title": "Code Club at RAF Cosford",
                "type": "photo",
                "url": "https://www.facebook.com/LichfieldCoders/photos/a.1570694216391006/1570694543057640/?type=3"
              },
              {
                "media": {
                  "image": {
                    "height": 720,
                    "src": "https://scontent.fbhx6-1.fna.fbcdn.net/v/t1.6435-9/35148087_1570694313057663_9134383638786342912_n.jpg?stp=dst-jpg_p720x720&_nc_cat=106&ccb=1-7&_nc_sid=cdbe9c&_nc_ohc=IKJbQ7n8MpYAX_BRcs1&_nc_ht=scontent.fbhx6-1.fna&edm=AKK4YLsEAAAA&oh=00_AfBnHeEDoWdgdTN_-XSB3gk959XymnVbNjki0sbjjrFF7A&oe=654E1C6E",
                    "width": 960
                  }
                },
                "target": {
                  "id": "1570694299724331",
                  "url": "https://www.facebook.com/LichfieldCoders/photos/a.1570694216391006/1570694299724331/?type=3"
                },
                "title": "Code Club at RAF Cosford",
                "type": "photo",
                "url": "https://www.facebook.com/LichfieldCoders/photos/a.1570694216391006/1570694299724331/?type=3"
              },
              {
                "media": {
                  "image": {
                    "height": 720,
                    "src": "https://scontent.fbhx6-1.fna.fbcdn.net/v/t1.6435-9/35077350_1570694496390978_7159435883697930240_n.jpg?stp=dst-jpg_p720x720&_nc_cat=110&ccb=1-7&_nc_sid=cdbe9c&_nc_ohc=q-5qhKj3yEMAX_Gakkl&_nc_ht=scontent.fbhx6-1.fna&edm=AKK4YLsEAAAA&oh=00_AfCCnglW_prkPjK84aiG4KPwsIXzCltQxZO753MWbSsPTg&oe=654E011F",
                    "width": 960
                  }
                },
                "target": {
                  "id": "1570694489724312",
                  "url": "https://www.facebook.com/LichfieldCoders/photos/a.1570694216391006/1570694489724312/?type=3"
                },
                "title": "Code Club at RAF Cosford",
                "type": "photo",
                "url": "https://www.facebook.com/LichfieldCoders/photos/a.1570694216391006/1570694489724312/?type=3"
              },
              {
                "media": {
                  "image": {
                    "height": 720,
                    "src": "https://scontent.fbhx6-1.fna.fbcdn.net/v/t1.6435-9/35144082_1570694246391003_7878080222665375744_n.jpg?stp=dst-jpg_p720x720&_nc_cat=106&ccb=1-7&_nc_sid=cdbe9c&_nc_ohc=FYb3H_eBV7MAX8ASlv0&_nc_ht=scontent.fbhx6-1.fna&edm=AKK4YLsEAAAA&oh=00_AfBUuXLQYzk3K97QUNfGwzNRsxAMqsO3eLsUaG5qEhw92g&oe=654E2F60",
                    "width": 960
                  }
                },
                "target": {
                  "id": "1570694243057670",
                  "url": "https://www.facebook.com/LichfieldCoders/photos/a.1570694216391006/1570694243057670/?type=3"
                },
                "title": "Code Club at RAF Cosford",
                "type": "photo",
                "url": "https://www.facebook.com/LichfieldCoders/photos/a.1570694216391006/1570694243057670/?type=3"
              },
              {
                "media": {
                  "image": {
                    "height": 720,
                    "src": "https://scontent.fbhx6-1.fna.fbcdn.net/v/t1.6435-9/35078591_1570694303057664_8118126073687834624_n.jpg?stp=dst-jpg_p720x720&_nc_cat=105&ccb=1-7&_nc_sid=cdbe9c&_nc_ohc=Ud-XEOz2KVgAX8u2dgt&_nc_ht=scontent.fbhx6-1.fna&edm=AKK4YLsEAAAA&oh=00_AfB66_yMpEdx_c2ItGPSVvr7TRTufufvmG2hTAjs83oK_Q&oe=654E1833",
                    "width": 960
                  }
                },
                "target": {
                  "id": "1570694293057665",
                  "url": "https://www.facebook.com/LichfieldCoders/photos/a.1570694216391006/1570694293057665/?type=3"
                },
                "title": "Code Club at RAF Cosford",
                "type": "photo",
                "url": "https://www.facebook.com/LichfieldCoders/photos/a.1570694216391006/1570694293057665/?type=3"
              },
              {
                "media": {
                  "image": {
                    "height": 720,
                    "src": "https://scontent.fbhx6-1.fna.fbcdn.net/v/t1.6435-9/35071115_1570694633057631_7554483410761154560_n.jpg?stp=dst-jpg_p720x720&_nc_cat=111&ccb=1-7&_nc_sid=cdbe9c&_nc_ohc=WFvyc5yDWd0AX-LktpN&_nc_ht=scontent.fbhx6-1.fna&edm=AKK4YLsEAAAA&oh=00_AfCGZtC60qm_iCl33Twc1_corNOQaAAgwFm6jLdk64gtnQ&oe=654E1F88",
                    "width": 960
                  }
                },
                "target": {
                  "id": "1570694626390965",
                  "url": "https://www.facebook.com/LichfieldCoders/photos/a.1570694216391006/1570694626390965/?type=3"
                },
                "title": "Code Club at RAF Cosford",
                "type": "photo",
                "url": "https://www.facebook.com/LichfieldCoders/photos/a.1570694216391006/1570694626390965/?type=3"
              }
            ]
          },
          "title": "Code Club at RAF Cosford",
          "type": "new_album",
          "url": "https://www.facebook.com/media/set/?set=ms.c.eJxNzVEOwFAERNEdNRjGs%7E%3B%7E_NNSFP%7E_3viDo0UllMgkYQ%7E%3BOuBKlNThAirNoXnBgigVsQuYpL4kJ8GF8P7ishvVF9BNziQ7apPkL2lgXKD1W8YLdGwpUg%7E-%7E-.bps.a.1570694216391006&type=1"
        }
      ]
    },
    "created_time": "2018-06-11T20:44:30+0000",
    "id": "1481985248595237_5195406677253057",
    "message": "On Sunday Jonathon and I took Code Club to the Cosford Air Show. A great day was had by all."
  },
  {
    "created_time": "2018-05-26T18:41:56+0000",
    "id": "1481985248595237_1555180067942421",
    "message": "Hello everyone. We are starting a new session on Tuesday June 5th. Please contact Yvonne Smith at Lichfield Library to register your interest. Age limit is 9-13. We will be following the Code Club Curriculum, using Scratch initially. These sessions are best suited to beginners."
  },
  {
    "created_time": "2018-05-11T15:11:57+0000",
    "id": "1481985248595237_1541258649334563",
    "message": "Hello Everybody, I am sorry we are unable to host our Saturday Code Club session this month. I think we will re-asses after the Library move now. Monday sessions are unaffected and next session is Monday 14th May. Don\u2019t hesitate to contact us if you have any questions. Happy Coding, Stewart & Johnathon \ud83d\ude0a"
  },
  {
    "created_time": "2018-05-09T21:59:38+0000",
    "id": "1481985248595237_1539736606153434",
    "message": "Aiming to be in Lichfield Library on Saturday 12th May. \ud83d\ude0a"
  },
  {
    "attachments": {
      "data": [
        {
          "media": {
            "image": {
              "height": 405,
              "src": "https://scontent.fbhx6-1.fna.fbcdn.net/v/t15.5256-10/28760015_1531514030309025_8583657222418989056_n.jpg?stp=dst-jpg_s720x720&_nc_cat=103&ccb=1-7&_nc_sid=ad6a45&_nc_ohc=mmbRrkZK7l4AX9hzlsF&_nc_ht=scontent.fbhx6-1.fna&edm=AKK4YLsEAAAA&oh=00_AfDuWjIyNlGBwl6qFLA8-heBFGXK_xjVTrCV0dxUACWk2g&oe=652B8101",
              "width": 720
            }
          },
          "target": {
            "id": "1531511846975910",
            "url": "https://www.facebook.com/720665616418529/videos/1531511846975910"
          },
          "type": "video_inline",
          "url": "https://www.facebook.com/720665616418529/videos/1531511846975910"
        }
      ]
    },
    "created_time": "2018-04-30T19:03:31+0000",
    "id": "1481985248595237_1531511846975910",
    "message": "Here is one of our coders games in action. Here we are using loops and conditional code to give the illusion of moving traffic."
  },
  {
    "attachments": {
      "data": [
        {
          "media": {
            "image": {
              "height": 720,
              "src": "https://scontent.fbhx6-1.fna.fbcdn.net/v/t1.6435-9/31513887_1531511070309321_5594208608280641536_n.jpg?_nc_cat=106&ccb=1-7&_nc_sid=dd63ad&_nc_ohc=UcU5gB2_oaIAX_ShLUS&_nc_ht=scontent.fbhx6-1.fna&edm=AKK4YLsEAAAA&oh=00_AfAERklIXvYcF5JCJKqx2qiGRVB3yU3xhMK1qha0VQeqNQ&oe=654E163D",
              "width": 960
            }
          },
          "subattachments": {
            "data": [
              {
                "media": {
                  "image": {
                    "height": 720,
                    "src": "https://scontent.fbhx6-1.fna.fbcdn.net/v/t1.6435-9/31513887_1531511070309321_5594208608280641536_n.jpg?_nc_cat=106&ccb=1-7&_nc_sid=dd63ad&_nc_ohc=UcU5gB2_oaIAX_ShLUS&_nc_ht=scontent.fbhx6-1.fna&edm=AKK4YLsEAAAA&oh=00_AfAERklIXvYcF5JCJKqx2qiGRVB3yU3xhMK1qha0VQeqNQ&oe=654E163D",
                    "width": 960
                  }
                },
                "target": {
                  "id": "1531511066975988",
                  "url": "https://www.facebook.com/LichfieldCoders/photos/a.1494843043976124/1531511066975988/?type=3"
                },
                "type": "photo",
                "url": "https://www.facebook.com/LichfieldCoders/photos/a.1494843043976124/1531511066975988/?type=3"
              },
              {
                "media": {
                  "image": {
                    "height": 720,
                    "src": "https://scontent.fbhx6-1.fna.fbcdn.net/v/t1.6435-9/31531410_1531511090309319_1073086536544681984_n.jpg?stp=dst-jpg_p720x720&_nc_cat=102&ccb=1-7&_nc_sid=dd63ad&_nc_ohc=APXSPgNgoBQAX9J84i4&_nc_ht=scontent.fbhx6-1.fna&edm=AKK4YLsEAAAA&oh=00_AfCxCW94FHVKxPn-8lioESnJNBq3bqnc9HjWrSbZTIBVbQ&oe=654E24B3",
                    "width": 802
                  }
                },
                "target": {
                  "id": "1531511086975986",
                  "url": "https://www.facebook.com/LichfieldCoders/photos/a.1494843043976124/1531511086975986/?type=3"
                },
                "type": "photo",
                "url": "https://www.facebook.com/LichfieldCoders/photos/a.1494843043976124/1531511086975986/?type=3"
              },
              {
                "media": {
                  "image": {
                    "height": 720,
                    "src": "https://scontent.fbhx6-1.fna.fbcdn.net/v/t1.6435-9/31646839_1531511080309320_2382997921978122240_n.jpg?_nc_cat=108&ccb=1-7&_nc_sid=dd63ad&_nc_ohc=9gQ62fQDpiMAX8Q8GJy&_nc_ht=scontent.fbhx6-1.fna&edm=AKK4YLsEAAAA&oh=00_AfDCCBuIlk-0lUutM90juhKKXxsOqeLyQkuaeHs8-daH0A&oe=654E28FC",
                    "width": 960
                  }
                },
                "target": {
                  "id": "1531511073642654",
                  "url": "https://www.facebook.com/LichfieldCoders/photos/a.1494843043976124/1531511073642654/?type=3"
                },
                "type": "photo",
                "url": "https://www.facebook.com/LichfieldCoders/photos/a.1494843043976124/1531511073642654/?type=3"
              },
              {
                "media": {
                  "image": {
                    "height": 720,
                    "src": "https://scontent.fbhx6-1.fna.fbcdn.net/v/t1.6435-9/31676563_1531511083642653_3117012591688286208_n.jpg?stp=dst-jpg_p720x720&_nc_cat=102&ccb=1-7&_nc_sid=dd63ad&_nc_ohc=7XQL_44CW5QAX8fgPUi&_nc_ht=scontent.fbhx6-1.fna&edm=AKK4YLsEAAAA&oh=00_AfA64EiqVwK87-lfBNklL7nUB04z28ruKgZZRJpV9DPDww&oe=654E37E8",
                    "width": 871
                  }
                },
                "target": {
                  "id": "1531511076975987",
                  "url": "https://www.facebook.com/LichfieldCoders/photos/a.1494843043976124/1531511076975987/?type=3"
                },
                "type": "photo",
                "url": "https://www.facebook.com/LichfieldCoders/photos/a.1494843043976124/1531511076975987/?type=3"
              }
            ]
          },
          "target": {
            "id": "1531511123642649",
            "url": "https://www.facebook.com/1481985248595237/posts/1531511123642649/"
          },
          "title": "Photos from Curborough Community Centre Code Club's post",
          "type": "album",
          "url": "https://www.facebook.com/1481985248595237/posts/1531511123642649/"
        }
      ]
    },
    "created_time": "2018-04-30T19:00:47+0000",
    "id": "1481985248595237_1531511123642649",
    "message": "Some of our activities tonight included Scratch games and an introduction to Python programming."
  },
  {
    "attachments": {
      "data": [
        {
          "description": "Well Done everyone. Some great coding and animations over the past few months. \ud83d\ude0a",
          "media": {
            "image": {
              "height": 532,
              "src": "https://scontent.fbhx6-1.fna.fbcdn.net/v/t1.6435-9/31676628_1531509133642848_1820124191341412352_n.jpg?_nc_cat=104&ccb=1-7&_nc_sid=dd63ad&_nc_ohc=S3FxL6mY4zQAX_JRPIh&_nc_ht=scontent.fbhx6-1.fna&edm=AKK4YLsEAAAA&oh=00_AfCyYZ4LOf8q4Tw1IMExE2S3JFG3hluVU5buTkqfiWZEmw&oe=654E12EC",
              "width": 960
            }
          },
          "target": {
            "id": "1531509130309515",
            "url": "https://www.facebook.com/LichfieldCoders/photos/a.1494843043976124/1531509130309515/?type=3"
          },
          "type": "photo",
          "url": "https://www.facebook.com/LichfieldCoders/photos/a.1494843043976124/1531509130309515/?type=3"
        }
      ]
    },
    "created_time": "2018-04-30T18:57:45+0000",
    "id": "1481985248595237_1531509153642846",
    "message": "Well Done everyone. Some great coding and animations over the past few months. \ud83d\ude0a"
  },
  {
    "created_time": "2018-04-23T15:19:20+0000",
    "id": "1481985248595237_1524990984294663",
    "message": "Sorry Folks Code Club is cancelled tonight. See you all next week."
  },
  {
    "attachments": {
      "data": [
        {
          "description": "A great turn out tonight for our Monday Night Code Club sessions. Lots of great ideas going on with Scratch tonight. Home made games and animations. Nice to see everyone using lots of different code constructs such as loops and broadcast events in their code. Well Done everyone. I think we will be dishing out some certificates next week :-)",
          "media": {
            "image": {
              "height": 720,
              "src": "https://scontent.fbhx6-1.fna.fbcdn.net/v/t1.6435-9/30728885_1518815894912172_2451366852073357312_n.png?stp=dst-png_p720x720&_nc_cat=110&ccb=1-7&_nc_sid=730e14&_nc_ohc=4kbAVrLE09cAX8jjcwD&_nc_ht=scontent.fbhx6-1.fna&edm=AKK4YLsEAAAA&oh=00_AfCXrcPEF3qudbuZwGfW7qHtRkaKh7vdbE713abq8kD1VA&oe=654E1481",
              "width": 1019
            }
          },
          "target": {
            "id": "1518815888245506",
            "url": "https://www.facebook.com/LichfieldCoders/photos/a.1482002635260165/1518815888245506/?type=3"
          },
          "type": "photo",
          "url": "https://www.facebook.com/LichfieldCoders/photos/a.1482002635260165/1518815888245506/?type=3"
        }
      ]
    },
    "created_time": "2018-04-16T19:42:24+0000",
    "id": "1481985248595237_1518817894911972",
    "message": "A great turn out tonight for our Monday Night Code Club sessions. Lots of great ideas going on with Scratch tonight. Home made games and animations. Nice to see everyone using lots of different code constructs such as loops and broadcast events in their code. Well Done everyone. I think we will be dishing out some certificates next week :-)"
  },
  {
    "attachments": {
      "data": [
        {
          "media": {
            "image": {
              "height": 720,
              "src": "https://scontent.fbhx6-1.fna.fbcdn.net/v/t1.6435-9/30739560_1518808328246262_4351405554271256576_n.jpg?stp=dst-jpg_p720x720&_nc_cat=100&ccb=1-7&_nc_sid=730e14&_nc_ohc=6aumL12OTfoAX9Rd2bf&_nc_oc=AQk2nu215QY5w2udo88Yy6xU3nhP7rUdRpzkOMiGHRXJYI9WZiIZZmqoUbusP2uW6dc&_nc_ht=scontent.fbhx6-1.fna&edm=AKK4YLsEAAAA&oh=00_AfAj0vcFw-oh1gPZvfJ2Sl5H3C0ZU9ZlNDpKjcv4lH4LNw&oe=654E2633",
              "width": 960
            }
          },
          "subattachments": {
            "data": [
              {
                "description": "Coding an analog clock in Scratch. We decided that testing the hour hand first was not the best idea. Our young programmers decided to speed the second hand up to count milli-seconds. A great way to see the minute and hour hand changing!",
                "media": {
                  "image": {
                    "height": 720,
                    "src": "https://scontent.fbhx6-1.fna.fbcdn.net/v/t1.6435-9/30739560_1518808328246262_4351405554271256576_n.jpg?stp=dst-jpg_p720x720&_nc_cat=100&ccb=1-7&_nc_sid=730e14&_nc_ohc=6aumL12OTfoAX9Rd2bf&_nc_oc=AQk2nu215QY5w2udo88Yy6xU3nhP7rUdRpzkOMiGHRXJYI9WZiIZZmqoUbusP2uW6dc&_nc_ht=scontent.fbhx6-1.fna&edm=AKK4YLsEAAAA&oh=00_AfAj0vcFw-oh1gPZvfJ2Sl5H3C0ZU9ZlNDpKjcv4lH4LNw&oe=654E2633",
                    "width": 960
                  }
                },
                "target": {
                  "id": "1518808321579596",
                  "url": "https://www.facebook.com/LichfieldCoders/photos/a.1482002635260165/1518808321579596/?type=3"
                },
                "type": "photo",
                "url": "https://www.facebook.com/LichfieldCoders/photos/a.1482002635260165/1518808321579596/?type=3"
              },
              {
                "description": "Here we are using a \u00a32 accelerometer connected to a Raspberry PI to control the aircraft on the screen. This simple game was written using the PyGame library.",
                "media": {
                  "image": {
                    "height": 720,
                    "src": "https://scontent.fbhx6-1.fna.fbcdn.net/v/t1.6435-9/30714043_1518808314912930_2996283663747907584_n.jpg?stp=dst-jpg_p720x720&_nc_cat=104&ccb=1-7&_nc_sid=730e14&_nc_ohc=ouJ7nb6G548AX8xWl2O&_nc_ht=scontent.fbhx6-1.fna&edm=AKK4YLsEAAAA&oh=00_AfCpjbV3wNYvvt4x4UJcsGpXhlSC1oluNcNy0BpWqVFHzw&oe=654E112A",
                    "width": 960
                  }
                },
                "target": {
                  "id": "1518808311579597",
                  "url": "https://www.facebook.com/LichfieldCoders/photos/a.1482002635260165/1518808311579597/?type=3"
                },
                "type": "photo",
                "url": "https://www.facebook.com/LichfieldCoders/photos/a.1482002635260165/1518808311579597/?type=3"
              },
              {
                "description": "Here we are using ModKit to program a VEX IQ Robot. The programming is based on Scratch, so it was very familiar to our young coders. One of our programmers discovered the joys of recursion, when the robot decided to wrap itself around the programming cable. This proved a great insight into event driven coding and a great test of our reaction speed to reach for the STOP button. :-)",
                "media": {
                  "image": {
                    "height": 682,
                    "src": "https://scontent.fbhx6-1.fna.fbcdn.net/v/t1.6435-9/30714031_1518808304912931_6236265026001305600_n.jpg?_nc_cat=108&ccb=1-7&_nc_sid=730e14&_nc_ohc=HdQT0aHXI_0AX8iHQ8X&_nc_ht=scontent.fbhx6-1.fna&edm=AKK4YLsEAAAA&oh=00_AfCP2NPrYYqXF4reS9QadG9-wZOQuWwPB1rjjNEX985IKw&oe=654E2F56",
                    "width": 1280
                  }
                },
                "target": {
                  "id": "1518808301579598",
                  "url": "https://www.facebook.com/LichfieldCoders/photos/a.1482002635260165/1518808301579598/?type=3"
                },
                "type": "photo",
                "url": "https://www.facebook.com/LichfieldCoders/photos/a.1482002635260165/1518808301579598/?type=3"
              }
            ]
          },
          "target": {
            "id": "1518809071579521",
            "url": "https://www.facebook.com/1481985248595237/posts/1518809071579521/"
          },
          "title": "Photos from Curborough Community Centre Code Club's post",
          "type": "album",
          "url": "https://www.facebook.com/1481985248595237/posts/1518809071579521/"
        }
      ]
    },
    "created_time": "2018-04-16T19:26:44+0000",
    "id": "1481985248595237_1518809071579521",
    "message": "Saturday Code Club saw us programming the VEX IQ Robot and Johnathon helping with some complex Scratch programming."
  },
  {
    "attachments": {
      "data": [
        {
          "description": "Updating Raspberry PIs ready for next weeks Saturday session.",
          "media": {
            "image": {
              "height": 720,
              "src": "https://scontent.fbhx6-1.fna.fbcdn.net/v/t1.6435-9/30221668_1510159365777825_3625405284945494016_n.jpg?_nc_cat=102&ccb=1-7&_nc_sid=dd63ad&_nc_ohc=lE__TpFSmDUAX8yOaWj&_nc_ht=scontent.fbhx6-1.fna&edm=AKK4YLsEAAAA&oh=00_AfDP9hPZAJaQNcz6esCI6zzfaPBPnCu3mpFs7C22OB61Kg&oe=654E1843",
              "width": 960
            }
          },
          "target": {
            "id": "1510159362444492",
            "url": "https://www.facebook.com/LichfieldCoders/photos/a.1494843043976124/1510159362444492/?type=3"
          },
          "type": "photo",
          "url": "https://www.facebook.com/LichfieldCoders/photos/a.1494843043976124/1510159362444492/?type=3"
        }
      ]
    },
    "created_time": "2018-04-07T15:59:32+0000",
    "id": "1481985248595237_1510159399111155",
    "message": "Updating Raspberry PIs ready for next weeks Saturday session."
  },
  {
    "attachments": {
      "data": [
        {
          "description": "Guides for setting up your Raspberry Pi correctly.",
          "media": {
            "image": {
              "height": 400,
              "src": "https://external.fbhx6-1.fna.fbcdn.net/emg1/v/t13/8646999205040786924?url=https%3A%2F%2Fwww.facebook.com%2Fads%2Fimage%2F%3Fd%3DAQImjsh_3TDs3TWgPdOJN93MMmrDQHmC2YIEdc5UopdQqgBZvfun8r8hC3g0lBdW3cDOmCHKSy3gGBupepe3E_K1Hfy1XpDYuZKeUyM4FLrKwH6st2YktW7LL6v8qLZme_ycmkEN86Vdr1Ixa3V2R0D1&fb_obo=1&utld=facebook.com&stp=c0.5000x0.5000f_dst-emg0_p400x400_q75&ccb=13-1&oh=06_AbFmOrRnGYtdGRyr3IXPBZce0Q3BFyz0WlqgblFHuyxq2g&oe=65286219&_nc_sid=e609ca",
              "width": 400
            }
          },
          "target": {
            "url": "https://l.facebook.com/l.php?u=https%3A%2F%2Fpimylifeup.com%2Fcategory%2Fguides%2F&h=AT07HFUeUYARGJwEtUxoPuZFYy1gJiwRKPsqxcNN3VLrGF584Hoe6dBToe6l8YmDAUr_sf2IaXArXhPVWLSFn39bVB93a4q6k4P7VJhPypk6ldIa-LO-oruej90kE8Ua&s=1"
          },
          "title": "17+ Handy Raspberry Pi Guides",
          "type": "share",
          "url": "https://l.facebook.com/l.php?u=https%3A%2F%2Fpimylifeup.com%2Fcategory%2Fguides%2F&h=AT07HFUeUYARGJwEtUxoPuZFYy1gJiwRKPsqxcNN3VLrGF584Hoe6dBToe6l8YmDAUr_sf2IaXArXhPVWLSFn39bVB93a4q6k4P7VJhPypk6ldIa-LO-oruej90kE8Ua&s=1"
        }
      ]
    },
    "created_time": "2018-04-01T17:17:33+0000",
    "id": "1481985248595237_1504634402996988"
  }
]